addition_tushar/__init__.py
addition_tushar/main.py
addition_tushar-0.2.dist-info/METADATA
addition_tushar-0.2.dist-info/WHEEL
addition_tushar-0.2.dist-info/entry_points.txt
addition_tushar-0.2.dist-info/top_level.txt
addition_tushar-0.2.dist-info/RECORD
