Metadata-Version: 2.1
Name: addition-tushar
Version: 0.2
Summary: UNKNOWN
Home-page: UNKNOWN
License: UNKNOWN
Platform: UNKNOWN
Requires-Dist: numpy
Requires-Dist: pandas
